{"title":"Pendahuluan","markdown":{"headingText":"Pendahuluan","containsRefs":false,"markdown":"\n## Struktur Buku\n\nSurvei keanekaragaman hayati bertujuan untuk mendapatkan informasi tentang keberadaan dan kondisi satwa liar serta tumbuhan di suatu wilayah dalam periode tertentu. Secara umum, ada dua pendekatan utama dalam survei ini: inventarisasi dan monitoring, yang masing-masing memiliki tujuan dan metodologi yang berbeda.\n\n**Inventarisasi** berfokus pada pengumpulan informasi dasar mengenai keberadaan fauna dan/atau flora di suatu area. Tujuan utama dari kegiatan ini adalah untuk memperoleh data awal atau data dasar tentang spesies yang ada di suatu lokasi. Proses ini biasanya dilakukan satu kali dalam jangka waktu tertentu untuk memberikan konfirmasi awal tentang ada atau tidaknya spesies tertentu di lokasi tersebut.\n\nSementara itu, **monitoring** dilakukan secara berulang dalam periode waktu yang berbeda, misalnya beberapa kali dalam setahun atau pada musim yang berbeda di lanskap yang sama, dengan menggunakan metode yang sama. Monitoring bertujuan untuk mengamati pola, dinamika, atau perubahan dalam komunitas fauna dan flora seiring waktu. Selain itu, monitoring juga digunakan untuk mengevaluasi dampak dari kegiatan tertentu, seperti perambahan kawasan terhadap komunitas burung dan primata, atau pencemaran sungai terhadap populasi amfibi.\n\nBaik inventarisasi maupun monitoring memerlukan perencanaan yang cermat untuk memastikan data yang diperoleh akurat dan representatif. Di lingkungan yang kompleks seperti hutan tropis yang lebat di Indonesia, mengumpulkan data yang akurat mengenai jumlah dan distribusi spesies menjadi tantangan yang signifikan. Oleh karena itu, rancangan survei yang tepat sangat penting untuk memastikan sampel yang diperoleh benar-benar mewakili kondisi sebenarnya di lapangan.\n\nKualitas data sangat dipengaruhi oleh metode dan rancangan survei yang digunakan. Survei yang dirancang dengan buruk atau data yang dikumpulkan dengan metode yang tidak memadai dapat menghambat proses analisis dan interpretasi, yang pada gilirannya mengurangi keandalan hasil survei. Dengan demikian, perencanaan survei harus memperhitungkan metode analisis yang sesuai sejak awal agar hasil analisis dapat mendukung tujuan penelitian atau konservasi dengan valid dan dapat diandalkan.\n\nHasil survei yang berkualitas tinggi sangat penting untuk pengambilan keputusan yang tepat, terutama dalam upaya konservasi jangka panjang. Data yang dikumpulkan harus dikelola dan diarsipkan dengan baik untuk memastikan relevansi dan kegunaannya di masa depan. Tanpa pengelolaan data yang memadai, informasi berharga yang diperoleh dari survei berisiko hilang atau tidak dapat digunakan secara efektif.\n\nUntuk membantu para praktisi memahami dan menerapkan survei keanekaragaman hayati dengan baik, setiap bagian dari buku ini dibagi menjadi empat sub-bab utama yang saling berkaitan:\n\n1.  **Rancangan Survei**: Menguraikan metode dan strategi perencanaan survei yang efektif untuk mendapatkan data yang akurat dan representatif.\n\n2.  **Protokol Survei**: Menjelaskan prosedur standar untuk pelaksanaan survei di lapangan, termasuk teknik pengambilan sampel yang memastikan data dikumpulkan secara konsisten dan sistematis.\n\n3.  **Pengelolaan Data**: Menyajikan langkah-langkah pengelolaan dan pengarsipan data yang tepat untuk menjaga integritas, keamanan, dan aksesibilitas data dalam jangka panjang.\n\n4.  **Analisis Data**: Memberikan panduan dalam memilih dan menerapkan metode analisis data yang sesuai untuk menginterpretasikan hasil survei secara akurat dan informatif.\n\nSelain itu, pada bagian lampiran buku ini juga mencakup panduan tentang **format lembar data yang terstandarisasi**. Bagian ini membantu para praktisi memahami cara mencatat dan menyusun data secara konsisten, sehingga data dapat dengan mudah dianalisis menggunakan standar yang sama dan menjaga kualitas data minimum yang diperlukan.\n\nBagian lampiran juga menyediakan panduan **eksplorasi dan visualisasi data**, lengkap dengan latihan-latihan analisis menggunakan dataset contoh. Latihan ini dirancang untuk meningkatkan keterampilan praktis dalam mengolah dan menampilkan data survei secara efektif, dengan memanfaatkan **R sebagai perangkat utama** untuk analisis. Hal ini memungkinkan hasil analisis dapat direproduksi oleh pembaca lain, mendukung transparansi, dan keandalan data.\n\n## Keselamatan Kerja\n\nSelain memahami metode dan teknik survei yang tepat, aspek keselamatan kerja di lapangan tidak kalah pentingnya untuk diperhatikan. Survei keanekaragaman hayati sering kali dilakukan di daerah terpencil yang jauh dari akses sarana umum dan bantuan medis profesional. Oleh karena itu, penting untuk selalu waspada terhadap berbagai potensi bahaya yang mungkin terjadi selama kegiatan survei.\n\nDalam kondisi yang menantang ini, memahami dan mematuhi prinsip-prinsip keselamatan sangatlah penting untuk menjaga kesejahteraan seluruh anggota tim. Berikut ini adalah beberapa tips keselamatan kerja yang perlu diikuti oleh setiap anggota tim survei:\n\n-   **Selalu bekerja bersama tim:** Jangan pernah melakukan pengamatan sendirian; pastikan minimal ada satu anggota lain. Jika terjadi kecelakaan atau kondisi darurat, rekan kerja dapat memberikan pertolongan pertama dan evakuasi.\n\n-   **Beri tahu rencana perjalanan:** Sampaikan rencana perjalanan Anda kepada orang di luar tim survei. Rincikan jadwal harian dan waktu kembali. Ini penting agar mereka dapat memutuskan untuk melakukan evakuasi jika Anda belum kembali sesuai jadwal.\n\n-   **Persiapkan peralatan keselamatan:** Bawa peta, kompas, GPS, senter, dan alat penerang. Bawa peralatan pertolongan pertama, suplai makanan ekstra, dan perlengkapan keselamatan lain sesuai kebutuhan.\n\n-   **Pelatihan pertolongan pertama:** Pastikan seluruh anggota tim terlatih dalam memberikan pertolongan pertama baik melalui kursus singkat ataupun membawa tim medis profesional.\n\n-   **Siapkan jalur evakuasi:** Tentukan rute evakuasi, titik evakuasi terdekat, kendaraan, fasilitas medis, dan protokol komunikasi yang diperlukan.\n\n-   **Gunakan tenaga lokal:** Libatkan masyarakat lokal untuk memberikan informasi mengenai jalur dan kondisi medan yang berbahaya.\n\n-   **Hindari organisme dan area berbahaya:** Hindari menangkap hewan berbahaya, seperti ular berbisa, dan jauhi tumbuhan yang menyebabkan iritasi. Hindari area berbahaya seperti sungai yang berpotensi dihuni buaya atau membuat kamp di sekitar pohon yang terlihat sudah mati.\n\n-   **Perhatikan kebersihan:** Bersihkan luka kecil dengan air dan sabun antiseptik. Pastikan kebersihan dapur kamp untuk mencegah infeksi dan masalah pencernaan.\n\n-   **Gunakan akal sehat:** Hindari tindakan berisiko seperti menyeberang sungai deras tanpa pengaman atau memanjat tebing tanpa tali. Kenali batas kemampuan diri dan buat pilihan yang aman.\n","srcMarkdownNoYaml":""},"formats":{"html":{"identifier":{"display-name":"HTML","target-format":"html","base-format":"html"},"execute":{"fig-width":7,"fig-height":5,"fig-format":"retina","fig-dpi":96,"df-print":"default","error":false,"eval":true,"cache":null,"freeze":false,"echo":true,"output":true,"warning":true,"include":true,"keep-md":false,"keep-ipynb":false,"ipynb":null,"enabled":true,"daemon":null,"daemon-restart":false,"debug":false,"ipynb-filters":[],"ipynb-shell-interactivity":null,"plotly-connected":true,"docx":{"reference-doc":"FFI_Word Template.docx"},"engine":"markdown"},"render":{"keep-tex":false,"keep-typ":false,"keep-source":false,"keep-hidden":false,"prefer-html":true,"output-divs":true,"output-ext":"html","fig-align":"default","fig-pos":null,"fig-env":null,"code-fold":false,"code-overflow":"scroll","code-link":false,"code-line-numbers":false,"code-tools":false,"tbl-colwidths":"auto","merge-includes":true,"inline-includes":false,"preserve-yaml":false,"latex-auto-mk":true,"latex-auto-install":true,"latex-clean":true,"latex-min-runs":1,"latex-max-runs":10,"latex-makeindex":"makeindex","latex-makeindex-opts":[],"latex-tlmgr-opts":[],"latex-input-paths":[],"latex-output-dir":null,"link-external-icon":false,"link-external-newwindow":false,"self-contained-math":false,"format-resources":[],"notebook-links":true},"pandoc":{"standalone":true,"wrap":"none","default-image-extension":"png","to":"html","css":["theme.css","theme.scss"],"toc":true,"output-file":"01-pendahuluan.html"},"language":{"toc-title-document":"Table of contents","toc-title-website":"On this page","related-formats-title":"Other Formats","related-notebooks-title":"Notebooks","source-notebooks-prefix":"Source","other-links-title":"Other Links","code-links-title":"Code Links","launch-dev-container-title":"Launch Dev Container","launch-binder-title":"Launch Binder","article-notebook-label":"Article Notebook","notebook-preview-download":"Download Notebook","notebook-preview-download-src":"Download Source","notebook-preview-back":"Back to Article","manuscript-meca-bundle":"MECA Bundle","section-title-abstract":"Abstract","section-title-appendices":"Appendices","section-title-footnotes":"Footnotes","section-title-references":"References","section-title-reuse":"Reuse","section-title-copyright":"Copyright","section-title-citation":"Citation","appendix-attribution-cite-as":"For attribution, please cite this work as:","appendix-attribution-bibtex":"BibTeX citation:","appendix-view-license":"View License","title-block-author-single":"Author","title-block-author-plural":"Authors","title-block-affiliation-single":"Affiliation","title-block-affiliation-plural":"Affiliations","title-block-published":"Published","title-block-modified":"Modified","title-block-keywords":"Keywords","callout-tip-title":"Tip","callout-note-title":"Note","callout-warning-title":"Warning","callout-important-title":"Important","callout-caution-title":"Caution","code-summary":"Code","code-tools-menu-caption":"Code","code-tools-show-all-code":"Show All Code","code-tools-hide-all-code":"Hide All Code","code-tools-view-source":"View Source","code-tools-source-code":"Source Code","tools-share":"Share","tools-download":"Download","code-line":"Line","code-lines":"Lines","copy-button-tooltip":"Copy to Clipboard","copy-button-tooltip-success":"Copied!","repo-action-links-edit":"Edit this page","repo-action-links-source":"View source","repo-action-links-issue":"Report an issue","back-to-top":"Back to top","search-no-results-text":"No results","search-matching-documents-text":"matching documents","search-copy-link-title":"Copy link to search","search-hide-matches-text":"Hide additional matches","search-more-match-text":"more match in this document","search-more-matches-text":"more matches in this document","search-clear-button-title":"Clear","search-text-placeholder":"","search-detached-cancel-button-title":"Cancel","search-submit-button-title":"Submit","search-label":"Search","toggle-section":"Toggle section","toggle-sidebar":"Toggle sidebar navigation","toggle-dark-mode":"Toggle dark mode","toggle-reader-mode":"Toggle reader mode","toggle-navigation":"Toggle navigation","crossref-fig-title":"Figure","crossref-tbl-title":"Table","crossref-lst-title":"Listing","crossref-thm-title":"Theorem","crossref-lem-title":"Lemma","crossref-cor-title":"Corollary","crossref-prp-title":"Proposition","crossref-cnj-title":"Conjecture","crossref-def-title":"Definition","crossref-exm-title":"Example","crossref-exr-title":"Exercise","crossref-ch-prefix":"Chapter","crossref-apx-prefix":"Appendix","crossref-sec-prefix":"Section","crossref-eq-prefix":"Equation","crossref-lof-title":"List of Figures","crossref-lot-title":"List of Tables","crossref-lol-title":"List of Listings","environment-proof-title":"Proof","environment-remark-title":"Remark","environment-solution-title":"Solution","listing-page-order-by":"Order By","listing-page-order-by-default":"Default","listing-page-order-by-date-asc":"Oldest","listing-page-order-by-date-desc":"Newest","listing-page-order-by-number-desc":"High to Low","listing-page-order-by-number-asc":"Low to High","listing-page-field-date":"Date","listing-page-field-title":"Title","listing-page-field-description":"Description","listing-page-field-author":"Author","listing-page-field-filename":"File Name","listing-page-field-filemodified":"Modified","listing-page-field-subtitle":"Subtitle","listing-page-field-readingtime":"Reading Time","listing-page-field-wordcount":"Word Count","listing-page-field-categories":"Categories","listing-page-minutes-compact":"{0} min","listing-page-category-all":"All","listing-page-no-matches":"No matching items","listing-page-words":"{0} words","listing-page-filter":"Filter","draft":"Draft"},"metadata":{"lang":"en","fig-responsive":true,"quarto-version":"1.5.57","bibliography":["references.bib"],"editor":"visual","theme":{"light":"cosmo"},"fontsize":"1.1em","linestretch":1.7,"toc-title":"Daftar Isi","crossref":{"fig-title":"Gambar","fig-prefix":"Gambar","tbl-title":"Tabel","tbl-prefix":"Tabel","sec-prefix":"Bab","sec-labels":"alpha"},"author-title":"Penulis"},"extensions":{"book":{"multiFile":true}}}},"projectFormats":["html"]}