{"title":"Prakata","markdown":{"headingText":"Prakata","headingAttr":{"id":"","classes":["unnumbered"],"keyvalue":[]},"containsRefs":false,"markdown":"\n## Untuk siapa panduan ini?\n\nPanduan ini disusun bagi para praktisi konservasi, peneliti, mahasiswa, serta siapa saja yang memiliki ketertarikan dalam melakukan survei keanekaragaman hayati (kehati), khususnya di lingkup kerja **Fauna & Flora Indonesia Programme (FF’s IP)**.\n\nMelalui panduan ini, kami ingin menetapkan standar minimum yang seragam dan akurat dalam pemantauan kehati, sehingga data yang dihasilkan dapat menjadi landasan kuat dalam pengambilan keputusan ilmiah dan kebijakan konservasi.\n\nPanduan ini menguraikan pendekatan praktis untuk melakukan survei kehati, dengan fokus pada tiga bagian utama:\n\n1.  **Bioma Terestrial**\\\n    Membahas metode survei konvensional di daratan yang **memerlukan kehadiran langsung peneliti** di lapangan, seperti pemantauan burung (avifauna), reptil dan amfibi (herpetofauna), mamalia, serta vegetasi. Setiap metode dijelaskan langkah demi langkah, lengkap dengan kelebihan, keterbatasan, serta contoh penerapan.\n\n2.  **Bioma Laut (Marine)**\\\n    Mengulas secara ringkas metode survei untuk ekosistem laut, termasuk pengamatan terumbu karang, padang lamun, hingga survei fauna laut seperti ikan dan mamalia laut. Bagian ini memberikan gambaran awal sebagai landasan pengembangan panduan lebih lanjut di masa depan.\n\n3.  **Penggunaan Kamera Intai (*Camera Trap*)**\\\n    Walaupun kamera intai dapat digunakan di bioma terestrial, panduan ini memberikan pembahasan terpisah karena teknik pemasangan, pengambilan data, hingga analisisnya memiliki kompleksitas tersendiri.\n\n    Kami menyadari bahwa metode survei kehati terus berkembang seiring kemajuan teknologi dan ilmu pengetahuan. Oleh karena itu, panduan ini bersifat **living document** yang akan terus diperbarui berdasarkan masukan dan pengalaman para praktisi. Kami sangat terbuka terhadap saran, kritik, ataupun laporan isu dari para pembaca. Silakan kirimkan kontribusi Anda melalui[email](mailto:ryan.avriandy@fauna-flora.org) atau laman [github kami](https://github.com/ryanavri/surveikehati).\n\n## Hak Cipta dan Sitasi\n\nPanduan ini lahir berkat kerja keras dan kolaborasi **Tim Biodiversitas Fauna & Flora Indonesia Programme**, dengan dukungan banyak pihak, termasuk tim penyusun dan editor yang berkomitmen mendukung upaya konservasi keanekaragaman hayati.\n\nKontributor utama yang telah memberikan masukan dan dukungan dalam penyusunan panduan ini meliputi:\\\nAdy Kristanto, Andhy Sayogo, Andri Irawan, Arief Hamidi, Dwiyanto, Fransisca Noni, Jarian Permana, Ryan Avriandy, Yanuar Ishaq Dwi Cahyo, Yogi Satrio Wibowo, dan Zana Pandya Pratisara, bersama tim editor yang dipimpin oleh \\[Nama Editor akan dicantumkan kemudian\\].\n\nKami mendorong para pembaca untuk menyebarluaskan buku ini seluas-luasnya demi mendukung upaya konservasi dan pemantauan keanekaragaman hayati di berbagai lokasi. Buku ini boleh didistribusikan dan dibagikan, asalkan mencantumkan kredit kepada penyusun dan kontributor.\n\nUntuk sitasi, silakan gunakan format berikut:\n\n``` markdown\nFauna & Flora Indonesia Programme. (2025). Panduan Survei Keanekaragaman Hayati. (Versi 0.1). https://doi.org/10.59350/zs7da-17c67.\n```\n\n``` markdown\n@online{faunaflora2025,\n  author = {Fauna & Flora Indonesia Programme},\n  title = {Panduan Survei Keanekaragaman Hayati},\n  year = {2025},\n  version = {0.1},\n  publisher = {Fauna & Flora Indonesia Programme},\n  url = {https://doi.org/10.59350/zs7da-17c67},\n  doi = {10.59350/zs7da-17c67},\n  langid = {id}\n}\n```\n","srcMarkdownNoYaml":""},"formats":{"html":{"identifier":{"display-name":"HTML","target-format":"html","base-format":"html"},"execute":{"fig-width":7,"fig-height":5,"fig-format":"retina","fig-dpi":96,"df-print":"default","error":false,"eval":true,"cache":null,"freeze":false,"echo":true,"output":true,"warning":true,"include":true,"keep-md":false,"keep-ipynb":false,"ipynb":null,"enabled":true,"daemon":null,"daemon-restart":false,"debug":false,"ipynb-filters":[],"ipynb-shell-interactivity":null,"plotly-connected":true,"docx":{"reference-doc":"FFI_Word Template.docx"},"engine":"markdown"},"render":{"keep-tex":false,"keep-typ":false,"keep-source":false,"keep-hidden":false,"prefer-html":true,"output-divs":true,"output-ext":"html","fig-align":"default","fig-pos":null,"fig-env":null,"code-fold":false,"code-overflow":"scroll","code-link":false,"code-line-numbers":false,"code-tools":false,"tbl-colwidths":"auto","merge-includes":true,"inline-includes":false,"preserve-yaml":false,"latex-auto-mk":true,"latex-auto-install":true,"latex-clean":true,"latex-min-runs":1,"latex-max-runs":10,"latex-makeindex":"makeindex","latex-makeindex-opts":[],"latex-tlmgr-opts":[],"latex-input-paths":[],"latex-output-dir":null,"link-external-icon":false,"link-external-newwindow":false,"self-contained-math":false,"format-resources":[],"notebook-links":true},"pandoc":{"standalone":true,"wrap":"none","default-image-extension":"png","to":"html","css":["theme.css","theme.scss"],"toc":true,"output-file":"index.html"},"language":{"toc-title-document":"Table of contents","toc-title-website":"On this page","related-formats-title":"Other Formats","related-notebooks-title":"Notebooks","source-notebooks-prefix":"Source","other-links-title":"Other Links","code-links-title":"Code Links","launch-dev-container-title":"Launch Dev Container","launch-binder-title":"Launch Binder","article-notebook-label":"Article Notebook","notebook-preview-download":"Download Notebook","notebook-preview-download-src":"Download Source","notebook-preview-back":"Back to Article","manuscript-meca-bundle":"MECA Bundle","section-title-abstract":"Abstract","section-title-appendices":"Appendices","section-title-footnotes":"Footnotes","section-title-references":"References","section-title-reuse":"Reuse","section-title-copyright":"Copyright","section-title-citation":"Citation","appendix-attribution-cite-as":"For attribution, please cite this work as:","appendix-attribution-bibtex":"BibTeX citation:","appendix-view-license":"View License","title-block-author-single":"Author","title-block-author-plural":"Authors","title-block-affiliation-single":"Affiliation","title-block-affiliation-plural":"Affiliations","title-block-published":"Published","title-block-modified":"Modified","title-block-keywords":"Keywords","callout-tip-title":"Tip","callout-note-title":"Note","callout-warning-title":"Warning","callout-important-title":"Important","callout-caution-title":"Caution","code-summary":"Code","code-tools-menu-caption":"Code","code-tools-show-all-code":"Show All Code","code-tools-hide-all-code":"Hide All Code","code-tools-view-source":"View Source","code-tools-source-code":"Source Code","tools-share":"Share","tools-download":"Download","code-line":"Line","code-lines":"Lines","copy-button-tooltip":"Copy to Clipboard","copy-button-tooltip-success":"Copied!","repo-action-links-edit":"Edit this page","repo-action-links-source":"View source","repo-action-links-issue":"Report an issue","back-to-top":"Back to top","search-no-results-text":"No results","search-matching-documents-text":"matching documents","search-copy-link-title":"Copy link to search","search-hide-matches-text":"Hide additional matches","search-more-match-text":"more match in this document","search-more-matches-text":"more matches in this document","search-clear-button-title":"Clear","search-text-placeholder":"","search-detached-cancel-button-title":"Cancel","search-submit-button-title":"Submit","search-label":"Search","toggle-section":"Toggle section","toggle-sidebar":"Toggle sidebar navigation","toggle-dark-mode":"Toggle dark mode","toggle-reader-mode":"Toggle reader mode","toggle-navigation":"Toggle navigation","crossref-fig-title":"Figure","crossref-tbl-title":"Table","crossref-lst-title":"Listing","crossref-thm-title":"Theorem","crossref-lem-title":"Lemma","crossref-cor-title":"Corollary","crossref-prp-title":"Proposition","crossref-cnj-title":"Conjecture","crossref-def-title":"Definition","crossref-exm-title":"Example","crossref-exr-title":"Exercise","crossref-ch-prefix":"Chapter","crossref-apx-prefix":"Appendix","crossref-sec-prefix":"Section","crossref-eq-prefix":"Equation","crossref-lof-title":"List of Figures","crossref-lot-title":"List of Tables","crossref-lol-title":"List of Listings","environment-proof-title":"Proof","environment-remark-title":"Remark","environment-solution-title":"Solution","listing-page-order-by":"Order By","listing-page-order-by-default":"Default","listing-page-order-by-date-asc":"Oldest","listing-page-order-by-date-desc":"Newest","listing-page-order-by-number-desc":"High to Low","listing-page-order-by-number-asc":"Low to High","listing-page-field-date":"Date","listing-page-field-title":"Title","listing-page-field-description":"Description","listing-page-field-author":"Author","listing-page-field-filename":"File Name","listing-page-field-filemodified":"Modified","listing-page-field-subtitle":"Subtitle","listing-page-field-readingtime":"Reading Time","listing-page-field-wordcount":"Word Count","listing-page-field-categories":"Categories","listing-page-minutes-compact":"{0} min","listing-page-category-all":"All","listing-page-no-matches":"No matching items","listing-page-words":"{0} words","listing-page-filter":"Filter","draft":"Draft"},"metadata":{"lang":"en","fig-responsive":true,"quarto-version":"1.6.42","bibliography":["references.bib"],"editor":"visual","theme":{"light":"cosmo"},"fontsize":"1.1em","linestretch":1.7,"toc-title":"Daftar Isi","crossref":{"fig-title":"Gambar","fig-prefix":"Gambar","tbl-title":"Tabel","tbl-prefix":"Tabel","sec-prefix":"Bab","sec-labels":"alpha"},"author-title":"Penulis"},"extensions":{"book":{"multiFile":true}}}},"projectFormats":["html"]}